Lab09/Lab09.srcs/sources_1/new/alu_control.v
`timescale 1ns / 1ps
//////////////////////////////////////////////////////////////////////////////////
// Module Name: alu_control
// Description: ALU Control Unit for RISC-V single-cycle datapath.
//
// Inputs:  ALUOp[1:0], funct3[2:0], funct7[6:0]
// Output:  ALUControl[3:0]
//
// Truth Table:
//   ALUOp1 ALUOp0 | funct7[5] | funct3 | ALUControl | Operation
//     0      0    |     X     |   X    |    0010    | add      (ld / sd)
//     X      1    |     X     |   X    |    0110    | subtract (beq)
//     1      X    |     0     |  000   |    0010    | add      (R-type)
//     1      X    |     1     |  000   |    0110    | subtract (R-type)
//     1      X    |     0     |  111   |    0000    | AND      (R-type)
//     1      X    |     0     |  110   |    0001    | OR       (R-type)
//
// Don't-care inputs (X) are handled by not checking that bit in the condition.
// Invalid/unrecognized combinations output 4'b1111 as a visible error flag.
//////////////////////////////////////////////////////////////////////////////////

module alu_control(
    input  [1:0] ALUOp,
    input  [2:0] funct3,
    input  [6:0] funct7,
    output reg [3:0] ALUControl
);

    wire ALUOp1   = ALUOp[1];   // MSB
    wire ALUOp0   = ALUOp[0];   // LSB
    wire funct7_5 = funct7[5];  // I[30] - distinguishes add vs subtract in R-type

    always @(*) begin
    // Default flag
    ALUControl = 4'b1111;

    if (ALUOp == 2'b00) begin
        ALUControl = 4'b0010; // add (ld / sd)
    end 
    else if (ALUOp == 2'b01) begin
        ALUControl = 4'b0110; // subtract (beq)
    end 
    else if (ALUOp == 2'b10) begin
        // R-type decodes
        if      (funct7_5 == 1'b0 && funct3 == 3'b000) ALUControl = 4'b0010; // add
        else if (funct7_5 == 1'b1 && funct3 == 3'b000) ALUControl = 4'b0110; // subtract
        else if (funct7_5 == 1'b0 && funct3 == 3'b111) ALUControl = 4'b0000; // AND
        else if (funct7_5 == 1'b0 && funct3 == 3'b110) ALUControl = 4'b0001; // OR
    end
end
endmodule

Lab09/Lab09.srcs/sources_1/new/main_control.v
`timescale 1ns / 1ps
//////////////////////////////////////////////////////////////////////////////////
// Module Name: main_control
// Description: Main Control Unit for RISC-V single-cycle datapath.
//              Decodes opcode[6:0] and outputs all control signals.
//
// Truth Table:
//   opcode        | RegWrite ALUOp MemRead MemWrite ALUSrc MemtoReg Branch
//   0000011 (ld)  |    1      00      1       0       1       1       0
//   0100011 (sd)  |    0      00      0       1       1       1(X)    0
//   1100011 (beq) |    0      01      0       0       0       1(X)    1
//   0110011 (R)   |    1      10      0       0       0       0       0
//
// Don't-care (X) outputs are hardcoded to 1.
// Invalid/unrecognized opcodes output all 1s as a visible error flag.
//////////////////////////////////////////////////////////////////////////////////

module main_control(
    input  [6:0] opcode,
    output reg       RegWrite,
    output reg [1:0] ALUOp,
    output reg       MemRead,
    output reg       MemWrite,
    output reg       ALUSrc,
    output reg       MemtoReg,
    output reg       Branch
);

    always @(*) begin

        // Default: all 1s - invalid opcode flag
        RegWrite = 1'b1;
        ALUOp    = 2'b10;
        MemRead  = 1'b0;
        MemWrite = 1'b0;
        ALUSrc   = 1'b0;
        MemtoReg = 1'b0;
        Branch   = 1'b0;

        case (opcode)
            7'b0000011: begin  // ld
                RegWrite = 1'b1;
                ALUOp    = 2'b00;
                MemRead  = 1'b1;
                MemWrite = 1'b0;
                ALUSrc   = 1'b1;
                MemtoReg = 1'b1;  // defined
                Branch   = 1'b0;
            end
            7'b0100011: begin  // sd
                RegWrite = 1'b0;
                ALUOp    = 2'b00;
                MemRead  = 1'b0;
                MemWrite = 1'b1;
                ALUSrc   = 1'b1;
                MemtoReg = 1'b1;  // X -> 1
                Branch   = 1'b0;
            end
            7'b1100011: begin  // beq
                RegWrite = 1'b0;
                ALUOp    = 2'b01;
                MemRead  = 1'b0;
                MemWrite = 1'b0;
                ALUSrc   = 1'b0;
                MemtoReg = 1'b1;  // X -> 1
                Branch   = 1'b1;
            end
            7'b0110011: begin  // R-type
                RegWrite = 1'b1;
                ALUOp    = 2'b10;
                MemRead  = 1'b0;
                MemWrite = 1'b0;
                ALUSrc   = 1'b0;
                MemtoReg = 1'b0;  // defined
                Branch   = 1'b0;
            end
            // unrecognized opcode -> stays at all-1s default
        endcase
    end

endmodule

Lab09/Lab09.srcs/sim_1/new/tb_control.v
`timescale 1ns / 1ps
//////////////////////////////////////////////////////////////////////////////////
// Module Name: tb_control
// Description: Integrated testbench for main_control and alu_control.
//              ALUOp wire connects the two modules, mirroring real hardware.
//////////////////////////////////////////////////////////////////////////////////

module tb_control;

    // -----------------------------------------------------------------------
    // Stimulus Inputs
    // -----------------------------------------------------------------------
    reg  [6:0] opcode;
    reg  [2:0] funct3;
    reg  [6:0] funct7;

    // -----------------------------------------------------------------------
    // Internal Wires & Outputs
    // -----------------------------------------------------------------------
    wire       RegWrite;
    wire [1:0] ALUOp;       // Wire connecting main_control TO alu_control
    wire       MemRead;
    wire       MemWrite;
    wire       ALUSrc;
    wire       MemtoReg;
    wire       Branch;
    wire [3:0] ALUControl;

    // -----------------------------------------------------------------------
    // Instantiate main_control
    // -----------------------------------------------------------------------
    main_control uut_main (
        .opcode   (opcode),
        .RegWrite (RegWrite),
        .ALUOp    (ALUOp),     // Drives the wire
        .MemRead  (MemRead),
        .MemWrite (MemWrite),
        .ALUSrc   (ALUSrc),
        .MemtoReg (MemtoReg),
        .Branch   (Branch)
    );

    // -----------------------------------------------------------------------
    // Instantiate alu_control
    // -----------------------------------------------------------------------
    alu_control uut_alu (
        .ALUOp      (ALUOp),   // Receives from the wire
        .funct3     (funct3),
        .funct7     (funct7),
        .ALUControl (ALUControl)
    );

    // -----------------------------------------------------------------------
    // Waveform dump
    // -----------------------------------------------------------------------
    initial begin
        $dumpfile("tb_control.vcd");
        $dumpvars(0, tb_control);
    end

    // -----------------------------------------------------------------------
    // Task: check main control outputs
    // -----------------------------------------------------------------------
    task check_main;
        input [6:0]  op;
        input        exp_RegWrite;
        input [1:0]  exp_ALUOp;
        input        exp_MemRead;
        input        exp_MemWrite;
        input        exp_ALUSrc;
        input        exp_Branch;
        input [80:0] label;
        begin
            opcode = op;
            #10;
            $display("  [Main] %s | RegWrite=%b ALUOp=%b MemRead=%b MemWrite=%b ALUSrc=%b MemtoReg=%b Branch=%b",
                      label, RegWrite, ALUOp, MemRead, MemWrite, ALUSrc, MemtoReg, Branch);
            if (RegWrite !== exp_RegWrite) $display("  FAIL RegWrite: exp=%b got=%b", exp_RegWrite, RegWrite);
            if (ALUOp    !== exp_ALUOp)    $display("  FAIL ALUOp:    exp=%b got=%b", exp_ALUOp,    ALUOp);
            if (MemRead  !== exp_MemRead)  $display("  FAIL MemRead:  exp=%b got=%b", exp_MemRead,  MemRead);
            if (MemWrite !== exp_MemWrite) $display("  FAIL MemWrite: exp=%b got=%b", exp_MemWrite, MemWrite);
            if (ALUSrc   !== exp_ALUSrc)   $display("  FAIL ALUSrc:   exp=%b got=%b", exp_ALUSrc,   ALUSrc);
            if (Branch   !== exp_Branch)   $display("  FAIL Branch:   exp=%b got=%b", exp_Branch,   Branch);
        end
    endtask

    // -----------------------------------------------------------------------
    // Task: check ALU control output
    // -----------------------------------------------------------------------
    task check_alu;
        input [6:0]  op;     // Now uses opcode to naturally set ALUOp
        input [2:0]  f3;
        input [6:0]  f7;
        input [3:0]  exp_ctrl;
        input [80:0] label;
        begin
            opcode = op;
            funct3 = f3;
            funct7 = f7;
            #10;
            $display("    Opcode=%b funct7[5]=%b funct3=%b -> ALUControl=%b  %s",
                      op, f7[5], f3, ALUControl,
                      (ALUControl === exp_ctrl) ? "PASS" : "FAIL");
        end
    endtask

    // -----------------------------------------------------------------------
    // Stimulus
    // -----------------------------------------------------------------------
    initial begin

        // Initialize all inputs to known values
        opcode = 7'b0000000;
        funct3 = 3'b000;
        funct7 = 7'b0000000;
        #5;                       

        // ===================================================================
        // PART 1: Main Control Unit
        // ===================================================================
        $display("=== MAIN CONTROL UNIT ===");

        $display("-- ld (0000011) --");
        check_main(7'b0000011, 1, 2'b00, 1, 0, 1, 0, "ld");

        $display("-- sd (0100011) --");
        check_main(7'b0100011, 0, 2'b00, 0, 1, 1, 0, "sd");

        $display("-- beq (1100011) --");
        check_main(7'b1100011, 0, 2'b01, 0, 0, 0, 1, "beq");

        $display("-- R-type (0110011) --");
        check_main(7'b0110011, 1, 2'b10, 0, 0, 0, 0, "R-type");

        // ===================================================================
        // PART 2: ALU Control (Integrated test via Opcode)
        // ===================================================================
        $display("");
        $display("=== ALU CONTROL UNIT ===");

        // ALUOp=00 -> add (Test via ld opcode)
        $display("-- ALUOp=00 -> add (ld) --");
        check_alu(7'b0000011, 3'b000, 7'b0000000, 4'b0010, "ld f=0");
        check_alu(7'b0000011, 3'b000, 7'b0000000, 4'b0010, "ld f=1");

        // ALUOp=01 -> subtract (Test via beq opcode)
        $display("-- ALUOp=01 -> subtract (beq) --");
        check_alu(7'b1100011, 3'b000, 7'b0000000, 4'b0110, "beq f=0");
        check_alu(7'b1100011, 3'b000, 7'b0000000, 4'b0110, "beq f=1");

        // ALUOp=10 -> R-type computations (Test via R-type opcode)
        $display("-- ALUOp=10 -> R-type Operations --");
        check_alu(7'b0110011, 3'b000, 7'b0000000, 4'b0010, "R-add");
        check_alu(7'b0110011, 3'b000, 7'b0100000, 4'b0110, "R-sub");
        check_alu(7'b0110011, 3'b111, 7'b0000000, 4'b0000, "R-and");
        check_alu(7'b0110011, 3'b110, 7'b0000000, 4'b0001, "R-or");

        $display("");
        $display("=== SIMULATION COMPLETE ===");
        $finish;
    end

endmodule

Lab09/Lab09.sim/sim_1/behav/xsim/tb_control.vcd
$date
   Thu Mar 26 13:21:50 2026
$end
$version
  2020.1
$end
$timescale
  1ps
$end
$scope module tb_control $end
$var reg 7 ! opcode [6:0] $end
$var reg 3 " funct3 [2:0] $end
$var reg 7 # funct7 [6:0] $end
$var wire 1 $ RegWrite $end
$var wire 2 % ALUOp [1:0] $end
$var wire 1 & MemRead $end
$var wire 1 ' MemWrite $end
$var wire 1 ( ALUSrc $end
$var wire 1 ) MemtoReg $end
$var wire 1 * Branch $end
$var wire 4 + ALUControl [3:0] $end
$scope module uut_main $end
$var wire 7 , opcode [6:0] $end
$var reg 1 - RegWrite $end
$var reg 2 . ALUOp [1:0] $end
$var reg 1 / MemRead $end
$var reg 1 0 MemWrite $end
$var reg 1 1 ALUSrc $end
$var reg 1 2 MemtoReg $end
$var reg 1 3 Branch $end
$upscope $end
$scope module uut_alu $end
$var wire 2 % ALUOp [1:0] $end
$var wire 3 4 funct3 [2:0] $end
$var wire 7 5 funct7 [6:0] $end
$var reg 4 6 ALUControl [3:0] $end
$var wire 1 7 ALUOp1 $end
$var wire 1 8 ALUOp0 $end
$var wire 1 9 funct7_5 $end
$upscope $end
$scope task check_main $end
$var reg 7 : op [6:0] $end
$var reg 1 ; exp_RegWrite $end
$var reg 2 < exp_ALUOp [1:0] $end
$var reg 1 = exp_MemRead $end
$var reg 1 > exp_MemWrite $end
$var reg 1 ? exp_ALUSrc $end
$var reg 1 @ exp_Branch $end
$var reg 81 A label [80:0] $end
$upscope $end
$scope task check_alu $end
$var reg 7 B op [6:0] $end
$var reg 3 C f3 [2:0] $end
$var reg 7 D f7 [6:0] $end
$var reg 4 E exp_ctrl [3:0] $end
$var reg 81 F label [80:0] $end
$upscope $end
$upscope $end
$enddefinitions $end
#0
$dumpvars
b0 !
b0 "
b0 #
1$
b10 %
0&
0'
0(
0)
0*
b10 +
b0 ,
1-
b10 .
0/
00
01
02
03
b0 4
b0 5
b10 6
17
08
09
bx :
x;
bx <
x=
x>
x?
x@
bx A
bx B
bx C
bx D
bx E
bx F
$end
#5000
b11 !
b0 %
1&
1(
1)
b11 ,
1-
b0 .
1/
00
11
12
03
b10 6
07
b11 :
1;
b0 <
1=
0>
1?
0@
b110110001100100 A
#15000
b100011 !
0$
b0 %
0&
1'
b100011 ,
0-
b0 .
0/
10
11
12
03
b100011 :
0;
0=
1>
b111001101100100 A
#25000
b1100011 !
b1 %
0'
0(
1*
b110 +
b1100011 ,
0-
b1 .
0/
00
01
12
13
b110 6
18
b1100011 :
b1 <
0>
0?
1@
b11000100110010101110001 A
#35000
b110011 !
1$
b10 %
0)
0*
b10 +
b110011 ,
1-
b10 .
0/
00
01
02
03
b10 6
17
08
b110011 :
1;
b10 <
0@
b10100100010110101110100011110010111000001100101 A
#45000
b11 !
b0 "
b0 #
b0 %
1&
1(
1)
b11 ,
1-
b0 .
1/
00
11
12
03
b10 6
07
b11 B
b0 C
b0 D
b10 E
b11011000110010000100000011001100011110100110000 F
#55000
b11 !
b0 "
b0 #
b11011000110010000100000011001100011110100110001 F
#65000
b1100011 !
b0 "
b0 #
0$
b1 %
0&
0(
1*
b110 +
b1100011 ,
0-
b1 .
0/
00
01
12
13
b110 6
18
b1100011 B
b110 E
b1100010011001010111000100100000011001100011110100110000 F
#75000
b1100011 !
b0 "
b0 #
b1100010011001010111000100100000011001100011110100110001 F
#85000
b110011 !
b0 "
b0 #
1$
b10 %
0)
0*
b10 +
b110011 ,
1-
b10 .
0/
00
01
02
03
b10 6
17
08
b110011 B
b10 E
b101001000101101011000010110010001100100 F
#95000
b110011 !
b0 "
b100000 #
b110 +
b100000 5
b110 6
19
b100000 D
b110 E
b101001000101101011100110111010101100010 F
#105000
b110011 !
b111 "
b0 #
b0 +
b111 4
b0 5
b0 6
09
b111 C
b0 D
b0 E
b101001000101101011000010110111001100100 F
#115000
b110011 !
b110 "
b0 #
b1 +
b110 4
b1 6
b110 C
b1 E
b1010010001011010110111101110010 F
