Lab09/Lab09.srcs/sources_1/new/alu_control.v
`timescale 1ns / 1ps
module alu_control(
    input  [1:0] ALUOp,
    input  [2:0] funct3,
    input  [6:0] funct7,
    output reg [3:0] ALUControl
);

//    wire [6:0]func= funct7;  // Bit 30 of instruction - distinguishes ADD/SUB

    always @(*) begin
        ALUControl = 4'b0000; // Default to AND or safe state

        case(ALUOp)
            2'b00:
                // Load/Store: Always performs an addition for address calculation
                ALUControl = 4'b0010; 

            2'b01: 
                // Branch: Always performs a subtraction to compare values
                ALUControl = 4'b0110; 

            2'b10: begin 
                // R-type: Operation depends on funct3 and funct7
                case(funct3)
                    3'b000: begin
                        if (funct7== 7'b0100000) 
                            ALUControl = 4'b0110; // SUB
                        else 
                            ALUControl = 4'b0010; // ADD
                    end
                    3'b001:  ALUControl = 4'b0100; // SLL
                    3'b101:  ALUControl = 4'b0101; // SRL
                    3'b111:  ALUControl = 4'b0000; // AND
                    3'b110:  ALUControl = 4'b0001; // OR
                    3'b100:  ALUControl = 4'b0011; // XOR
                    default: ALUControl = 4'b0000;
                endcase
            end

            2'b11: begin 
                // I-type: Logic based on funct3 (e.g., ADDI)
                case(funct3)
                    3'b000:  ALUControl = 4'b0010; // ADDI
                    default: ALUControl = 4'b0000;
                endcase
            end

            default: ALUControl = 4'b0000;
        endcase
    end

endmodule

Lab09/Lab09.srcs/sources_1/new/main_control.v
`timescale 1ns / 1ps

module main_control(
    input  [6:0] opcode,
    output reg       RegWrite,
    output reg [1:0] ALUOp,
    output reg       MemRead,
    output reg       MemWrite,
    output reg       ALUSrc,
    output reg       MemtoReg,
    output reg       Branch
);
    
    always @(*) begin
        // Default values to prevent latches
        RegWrite = 0; 
        ALUSrc   = 0; 
        MemRead  = 0; 
        MemWrite = 0; 
        MemtoReg = 0; 
        Branch   = 0; 
        ALUOp    = 2'b00;

        case(opcode)
            7'b0110011: begin // R-type
                RegWrite = 1; 
                ALUOp    = 2'b10;
            end

            7'b0010011: begin // I-type (ADDI)
                RegWrite = 1; 
                ALUSrc   = 1; 
                ALUOp    = 2'b11;
            end

            7'b0000011: begin // Load (LW, LH, LB)
                RegWrite = 1; 
                ALUSrc   = 1; 
                MemRead  = 1; 
                MemtoReg = 1; 
                ALUOp    = 2'b00;
            end

            7'b0100011: begin // Store (SW, SH, SB)
                ALUSrc   = 1; 
                MemWrite = 1; 
                ALUOp    = 2'b00;
            end

            7'b1100011: begin // Branch (BEQ)
                Branch   = 1; 
                ALUOp    = 2'b01;
            end

            default: begin
                // Keeps safe zeros for undefined opcodes
            end
        endcase
    end

endmodule

Lab09/Lab09.srcs/sim_1/new/tb_control.v
`timescale 1ns / 1ps
//////////////////////////////////////////////////////////////////////////////////
// Module Name: tb_control
// Description: Integrated testbench for main_control and alu_control.
//              ALUOp wire connects the two modules, mirroring real hardware.
//////////////////////////////////////////////////////////////////////////////////

module tb_control;

    // -----------------------------------------------------------------------
    // Stimulus Inputs
    // -----------------------------------------------------------------------
    reg  [6:0] opcode;
    reg  [2:0] funct3;
    reg  [6:0] funct7;

    // -----------------------------------------------------------------------
    // Internal Wires & Outputs
    // -----------------------------------------------------------------------
    wire       RegWrite;
    wire [1:0] ALUOp;       // Wire connecting main_control TO alu_control
    wire       MemRead;
    wire       MemWrite;
    wire       ALUSrc;
    wire       MemtoReg;
    wire       Branch;
    wire [3:0] ALUControl;

    // -----------------------------------------------------------------------
    // Instantiate main_control
    // -----------------------------------------------------------------------
    main_control uut_main (
        .opcode   (opcode),
        .RegWrite (RegWrite),
        .ALUOp    (ALUOp),     // Drives the wire
        .MemRead  (MemRead),
        .MemWrite (MemWrite),
        .ALUSrc   (ALUSrc),
        .MemtoReg (MemtoReg),
        .Branch   (Branch)
    );

    // -----------------------------------------------------------------------
    // Instantiate alu_control
    // -----------------------------------------------------------------------
    alu_control uut_alu (
        .ALUOp      (ALUOp),   // Receives from the wire
        .funct3     (funct3),
        .funct7     (funct7),
        .ALUControl (ALUControl)
    );

    // -----------------------------------------------------------------------
    // Waveform dump
    // -----------------------------------------------------------------------
    initial begin
        $dumpfile("tb_control.vcd");
        $dumpvars(0, tb_control);
    end

    // -----------------------------------------------------------------------
    // Task: check main control outputs
    // -----------------------------------------------------------------------
    task check_main;
        input [6:0]  op;
        input        exp_RegWrite;
        input [1:0]  exp_ALUOp;
        input        exp_MemRead;
        input        exp_MemWrite;
        input        exp_ALUSrc;
        input        exp_Branch;
        input [80:0] label;
        begin
            opcode = op;
            #10;
            $display("  [Main] %s | RegWrite=%b ALUOp=%b MemRead=%b MemWrite=%b ALUSrc=%b MemtoReg=%b Branch=%b",
                      label, RegWrite, ALUOp, MemRead, MemWrite, ALUSrc, MemtoReg, Branch);
            if (RegWrite !== exp_RegWrite) $display("  FAIL RegWrite: exp=%b got=%b", exp_RegWrite, RegWrite);
            if (ALUOp    !== exp_ALUOp)    $display("  FAIL ALUOp:    exp=%b got=%b", exp_ALUOp,    ALUOp);
            if (MemRead  !== exp_MemRead)  $display("  FAIL MemRead:  exp=%b got=%b", exp_MemRead,  MemRead);
            if (MemWrite !== exp_MemWrite) $display("  FAIL MemWrite: exp=%b got=%b", exp_MemWrite, MemWrite);
            if (ALUSrc   !== exp_ALUSrc)   $display("  FAIL ALUSrc:   exp=%b got=%b", exp_ALUSrc,   ALUSrc);
            if (Branch   !== exp_Branch)   $display("  FAIL Branch:   exp=%b got=%b", exp_Branch,   Branch);
        end
    endtask

    // -----------------------------------------------------------------------
    // Task: check ALU control output
    // -----------------------------------------------------------------------
    task check_alu;
        input [6:0]  op;     // Now uses opcode to naturally set ALUOp
        input [2:0]  f3;
        input [6:0]  f7;
        input [3:0]  exp_ctrl;
        input [80:0] label;
        begin
            opcode = op;
            funct3 = f3;
            funct7 = f7;
            #10;
            $display("    Opcode=%b funct7[5]=%b funct3=%b -> ALUControl=%b  %s",
                      op, f7[5], f3, ALUControl,
                      (ALUControl === exp_ctrl) ? "PASS" : "FAIL");
        end
    endtask

    // -----------------------------------------------------------------------
    // Stimulus
    // -----------------------------------------------------------------------
    initial begin

        // Initialize all inputs to known values
        opcode = 7'b0000000;
        funct3 = 3'b000;
        funct7 = 7'b0000000;
        #5;                       

        // ===================================================================
        // PART 1: Main Control Unit
        // ===================================================================
        $display("=== MAIN CONTROL UNIT ===");

        $display("-- ld (0000011) --");
        check_main(7'b0000011, 1, 2'b00, 1, 0, 1, 0, "ld");

        $display("-- sd (0100011) --");
        check_main(7'b0100011, 0, 2'b00, 0, 1, 1, 0, "sd");

        $display("-- beq (1100011) --");
        check_main(7'b1100011, 0, 2'b01, 0, 0, 0, 1, "beq");

        $display("-- R-type (0110011) --");
        check_main(7'b0110011, 1, 2'b10, 0, 0, 0, 0, "R-type");

        // ===================================================================
        // PART 2: ALU Control (Integrated test via Opcode)
        // ===================================================================
        $display("");
        $display("=== ALU CONTROL UNIT ===");

        // ALUOp=00 -> add (Test via ld opcode)
        $display("-- ALUOp=00 -> add (ld) --");
        check_alu(7'b0000011, 3'b000, 7'b0000000, 4'b0010, "ld f=0");
        check_alu(7'b0000011, 3'b000, 7'b0000000, 4'b0010, "ld f=1");

        // ALUOp=01 -> subtract (Test via beq opcode)
        $display("-- ALUOp=01 -> subtract (beq) --");
        check_alu(7'b1100011, 3'b000, 7'b0000000, 4'b0110, "beq f=0");
        check_alu(7'b1100011, 3'b000, 7'b0000000, 4'b0110, "beq f=1");

        // ALUOp=10 -> R-type computations (Test via R-type opcode)
        $display("-- ALUOp=10 -> R-type Operations --");
        check_alu(7'b0110011, 3'b000, 7'b0000000, 4'b0010, "R-add");
        check_alu(7'b0110011, 3'b000, 7'b0100000, 4'b0110, "R-sub");
        check_alu(7'b0110011, 3'b111, 7'b0000000, 4'b0000, "R-and");
        check_alu(7'b0110011, 3'b110, 7'b0000000, 4'b0001, "R-or");

        $display("");
        $display("=== SIMULATION COMPLETE ===");
        $finish;
    end

endmodule

Lab09/Lab09.sim/sim_1/behav/xsim/tb_control.vcd
$date
   Thu Apr  2 20:32:47 2026
$end
$version
  2020.1
$end
$timescale
  1ps
$end
$scope module tb_control $end
$var reg 7 ! opcode [6:0] $end
$var reg 3 " funct3 [2:0] $end
$var reg 7 # funct7 [6:0] $end
$var wire 1 $ RegWrite $end
$var wire 2 % ALUOp [1:0] $end
$var wire 1 & MemRead $end
$var wire 1 ' MemWrite $end
$var wire 1 ( ALUSrc $end
$var wire 1 ) MemtoReg $end
$var wire 1 * Branch $end
$var wire 4 + ALUControl [3:0] $end
$scope module uut_main $end
$var wire 7 , opcode [6:0] $end
$var reg 1 - RegWrite $end
$var reg 2 . ALUOp [1:0] $end
$var reg 1 / MemRead $end
$var reg 1 0 MemWrite $end
$var reg 1 1 ALUSrc $end
$var reg 1 2 MemtoReg $end
$var reg 1 3 Branch $end
$upscope $end
$scope module uut_alu $end
$var wire 2 % ALUOp [1:0] $end
$var wire 3 4 funct3 [2:0] $end
$var wire 7 5 funct7 [6:0] $end
$var reg 4 6 ALUControl [3:0] $end
$upscope $end
$scope task check_main $end
$var reg 7 7 op [6:0] $end
$var reg 1 8 exp_RegWrite $end
$var reg 2 9 exp_ALUOp [1:0] $end
$var reg 1 : exp_MemRead $end
$var reg 1 ; exp_MemWrite $end
$var reg 1 < exp_ALUSrc $end
$var reg 1 = exp_Branch $end
$var reg 81 > label [80:0] $end
$upscope $end
$scope task check_alu $end
$var reg 7 ? op [6:0] $end
$var reg 3 @ f3 [2:0] $end
$var reg 7 A f7 [6:0] $end
$var reg 4 B exp_ctrl [3:0] $end
$var reg 81 C label [80:0] $end
$upscope $end
$upscope $end
$enddefinitions $end
#0
$dumpvars
b0 !
b0 "
b0 #
0$
b0 %
0&
0'
0(
0)
0*
b10 +
b0 ,
0-
b0 .
0/
00
01
02
03
b0 4
b0 5
b10 6
bx 7
x8
bx 9
x:
x;
x<
x=
bx >
bx ?
bx @
bx A
bx B
bx C
$end
#5000
b11 !
1$
1&
1(
1)
b11 ,
1-
b0 .
1/
00
11
12
03
b11 7
18
b0 9
1:
0;
1<
0=
b110110001100100 >
#15000
b100011 !
0$
0&
1'
0)
b100011 ,
0-
b0 .
0/
10
11
02
03
b100011 7
08
0:
1;
b111001101100100 >
#25000
b1100011 !
b1 %
0'
0(
1*
b110 +
b1100011 ,
0-
b1 .
0/
00
01
02
13
b110 6
b1100011 7
b1 9
0;
0<
1=
b11000100110010101110001 >
#35000
b110011 !
1$
b10 %
0*
b10 +
b110011 ,
1-
b10 .
0/
00
01
02
03
b10 6
b110011 7
18
b10 9
0=
b10100100010110101110100011110010111000001100101 >
#45000
b11 !
b0 "
b0 #
b0 %
1&
1(
1)
b11 ,
1-
b0 .
1/
00
11
12
03
b10 6
b11 ?
b0 @
b0 A
b10 B
b11011000110010000100000011001100011110100110000 C
#55000
b11 !
b0 "
b0 #
b11011000110010000100000011001100011110100110001 C
#65000
b1100011 !
b0 "
b0 #
0$
b1 %
0&
0(
0)
1*
b110 +
b1100011 ,
0-
b1 .
0/
00
01
02
13
b110 6
b1100011 ?
b110 B
b1100010011001010111000100100000011001100011110100110000 C
#75000
b1100011 !
b0 "
b0 #
b1100010011001010111000100100000011001100011110100110001 C
#85000
b110011 !
b0 "
b0 #
1$
b10 %
0*
b10 +
b110011 ,
1-
b10 .
0/
00
01
02
03
b10 6
b110011 ?
b10 B
b101001000101101011000010110010001100100 C
#95000
b110011 !
b0 "
b100000 #
b110 +
b100000 5
b110 6
b100000 A
b110 B
b101001000101101011100110111010101100010 C
#105000
b110011 !
b111 "
b0 #
b0 +
b111 4
b0 5
b0 6
b111 @
b0 A
b0 B
b101001000101101011000010110111001100100 C
#115000
b110011 !
b110 "
b0 #
b1 +
b110 4
b1 6
b110 @
b1 B
b1010010001011010110111101110010 C
